grokcore.security-4.1-py3.12-nspkg.pth
grokcore/security/__init__.py
grokcore/security/components.py
grokcore/security/directive.py
grokcore/security/ftesting.zcml
grokcore/security/interfaces.py
grokcore/security/meta.zcml
grokcore/security/testing.py
grokcore/security/util.py
grokcore/security/meta/__init__.py
grokcore/security/meta/permission.py
grokcore/security/meta/role.py
grokcore/security/tests/__init__.py
grokcore/security/tests/test_base.py
grokcore/security/tests/test_functional.py
grokcore/security/tests/base/__init__.py
grokcore/security/tests/base/permissions/__init__.py
grokcore/security/tests/base/permissions/directive.py
grokcore/security/tests/base/permissions/directive_fixture.py
grokcore/security/tests/base/role/__init__.py
grokcore/security/tests/base/role/missing_role_name.py
grokcore/security/tests/base/role/permissions.py
grokcore/security/tests/base/role/role_i18n.py
grokcore/security/tests/base/security/__init__.py
grokcore/security/tests/base/security/fallback.py
grokcore/security/tests/base/security/missing_permission.py
grokcore/security/tests/base/security/missing_permission_name.py
grokcore/security/tests/base/security/multiple_require.py
grokcore/security/tests/base/security/not_a_permissionclass.py
grokcore/security/tests/base/security/permission.py
grokcore/security/tests/base/security/protect_getattr.py
grokcore/security/tests/functional/__init__.py
grokcore/security/tests/functional/role/__init__.py
grokcore/security/tests/functional/role/roles.py
grokcore_security-4.1.dist-info/licenses/LICENSE.txt
grokcore_security-4.1.dist-info/METADATA
grokcore_security-4.1.dist-info/WHEEL
grokcore_security-4.1.dist-info/namespace_packages.txt
grokcore_security-4.1.dist-info/top_level.txt
grokcore_security-4.1.dist-info/RECORD
