Metadata-Version: 2.4
Name: grokcore.security
Version: 4.1
Summary: Grok-like configuration for Zope security components
Home-page: https://github.com/zopefoundation/grokcore.security
Author: Grok Team
Author-email: zope-dev@zope.dev
License: ZPL
Classifier: Intended Audience :: Developers
Classifier: Development Status :: 6 - Mature
Classifier: License :: OSI Approved :: Zope Public License
Classifier: Operating System :: OS Independent
Classifier: Programming Language :: Python :: 3
Classifier: Programming Language :: Python :: 3.9
Classifier: Programming Language :: Python :: 3.10
Classifier: Programming Language :: Python :: 3.11
Classifier: Programming Language :: Python :: 3.12
Classifier: Programming Language :: Python :: 3.13
Classifier: Programming Language :: Python :: Implementation :: CPython
Classifier: Programming Language :: Python :: Implementation :: PyPy
Requires-Python: >=3.9
License-File: LICENSE.txt
Requires-Dist: Chameleon>=2
Requires-Dist: grokcore.component>=2.1
Requires-Dist: martian>=0.13
Requires-Dist: setuptools
Requires-Dist: zope.component
Requires-Dist: zope.dottedname
Requires-Dist: zope.interface
Requires-Dist: zope.security
Provides-Extra: role
Requires-Dist: zope.securitypolicy; extra == "role"
Provides-Extra: test
Requires-Dist: grokcore.view[test]; extra == "test"
Requires-Dist: zope.app.wsgi; extra == "test"
Requires-Dist: zope.configuration; extra == "test"
Requires-Dist: zope.securitypolicy; extra == "test"
Requires-Dist: zope.testing; extra == "test"
Dynamic: author
Dynamic: author-email
Dynamic: classifier
Dynamic: description
Dynamic: home-page
Dynamic: license
Dynamic: license-file
Dynamic: provides-extra
Dynamic: requires-dist
Dynamic: requires-python
Dynamic: summary
